sphereob/__init__.py
sphereob/resources.py
sphereob/sphere_main.py
sphereob/sphere_response.py
sphereobmodel-0.1.0.dist-info/METADATA
sphereobmodel-0.1.0.dist-info/WHEEL
sphereobmodel-0.1.0.dist-info/entry_points.txt
sphereobmodel-0.1.0.dist-info/top_level.txt
sphereobmodel-0.1.0.dist-info/RECORD
